kurdish/__init__.py
kurdish/bizrokeRules.py
kurdish/ku.py
kurdish/punctuation.py
kurdish/vowelIssues.py
kurdish-1.1.5.dist-info/METADATA
kurdish-1.1.5.dist-info/WHEEL
kurdish-1.1.5.dist-info/top_level.txt
kurdish-1.1.5.dist-info/RECORD
