Metadata-Version: 2.1
Name: kurdish
Version: 1.1.5
Summary: Kurdish Language Library for transliteration from Arabic-based Kurdish to Latin-based Kurdish.
Home-page: https://github.com/dolanskurd/kurdish
Author: Dolan Hêriş
Author-email: dolanskurd@mail.com
License: MIT
Keywords: kurdish language module library converter digits characters persian farsi arabic latin english transliteration
Platform: UNKNOWN
Classifier: Topic :: Documentation
Classifier: Topic :: Printing
Classifier: License :: OSI Approved :: MIT License
Classifier: Programming Language :: Python
Classifier: Programming Language :: Python :: 3
Classifier: Programming Language :: Python :: 3.4
Classifier: Programming Language :: Python :: 3.5
Classifier: Programming Language :: Python :: 3.6
Classifier: Programming Language :: Python :: 3.7
Classifier: Programming Language :: Python :: 3.8
Classifier: Topic :: Software Development :: Libraries :: Python Modules
Classifier: Topic :: Text Editors :: Text Processing
Classifier: Topic :: Text Processing :: Fonts
Classifier: Topic :: Text Editors :: Word Processors
Classifier: Topic :: Utilities
Classifier: Intended Audience :: Developers
Classifier: Topic :: Software Development :: Libraries
Classifier: Topic :: Software Development :: Libraries :: Python Modules
